sora_extend/__init__.py
sora_extend/cli.py
sora_extend/constants.py
sora_extend/pipeline.py
sora_extend/planner.py
sora_extend/sora_api.py
sora_extend/video_utils.py
sora_extend-0.1.3.dist-info/WHEEL
sora_extend-0.1.3.dist-info/entry_points.txt
sora_extend-0.1.3.dist-info/METADATA
sora_extend-0.1.3.dist-info/RECORD
