Metadata-Version: 2.3
Name: sora-extend
Version: 0.1.3
Summary: AI-Planned, Scene-Exact Video Generation with Continuity using Sora 2
Author: Mason Hall
Author-email: Mason Hall <masonhall@gmail.com>
Requires-Dist: openai>=1.0.0
Requires-Dist: requests>=2.31.0
Requires-Dist: typer>=0.9.0
Requires-Dist: rich>=13.0.0
Requires-Dist: moviepy>=1.0.3
Requires-Dist: opencv-python-headless>=4.8.0
Requires-Dist: imageio>=2.31.0
Requires-Dist: imageio-ffmpeg>=0.4.9
Requires-Python: >=3.12
